{
    "version": "1.2.4",
    "architecture": {
        "32bit": {
            "url": "https://github.com/goreleaser/goreleaser/releases/download/v1.2.4/goreleaser_Windows_i386.zip",
            "bin": [
                "goreleaser.exe"
            ],
            "hash": "20e17168bdf1c2c14a618c2cce9146744c3588c456262518d03ebd921dce969f"
        },
        "64bit": {
            "url": "https://github.com/goreleaser/goreleaser/releases/download/v1.2.4/goreleaser_Windows_x86_64.zip",
            "bin": [
                "goreleaser.exe"
            ],
            "hash": "ee2054eaf2fbf75d3cf77ade737f8b1c6e0d06bca9e8d0071bd739eafbc93310"
        }
    },
    "homepage": "https://goreleaser.com",
    "license": "MIT",
    "description": "Deliver Go binaries as fast and easily as possible"
}